<?xml version="1.0"?>
<mujoco model="scene_20">
	<compiler angle="radian" />
	<include file="include/settings.xml" />
	<asset>
		<include file="include/assets.xml" />
		<include file="robot/include/robot_assets.xml" />
	</asset>
	<include file="include/defaults.xml" />
	<include file="include/custom_attributes_for_shelf_2.xml" />
	<worldbody>
		<include file="include/camera_and_lighting.xml" />
		<body name="object_1" pos="0.445477 0.239563 0.182613" quat="0.868487 -0.000011 0.000006 -0.495713">
			<geom friction="0.3 0.3 0.3" contype="3" conaffinity="3" mass="1." name="object_1" rgba="1 0 0. 1" size="0.03 0.05" type="cylinder" />
			<joint damping="0.5" stiffness="0.01" armature="0.1" name="object_1_free" type="free" />
		</body>
		<body name="object_2" pos="0.462217 0.086983 0.183094" quat="0.094294 0.000007 -0.000001 -0.995544">
			<geom friction="0.3 0.3 0.3" contype="3" conaffinity="3" mass="1." name="object_2" rgba="1 0 0. 1" size="0.03 0.05" type="cylinder" />
			<joint damping="0.5" stiffness="0.01" armature="0.1" name="object_2_free" type="free" />
		</body>
		<body name="object_3" pos="0.511354 0.116476 0.182623" quat="1.000000 -0.000013 0.000016 -0.000024">
			<geom friction="0.3 0.3 0.3" contype="3" conaffinity="3" mass="1." name="object_3" rgba="0 1 0. 1" size="0.03 0.05" type="cylinder" />
			<joint damping="0.5" stiffness="0.01" armature="0.1" name="object_3_free" type="free" />
		</body>
		<body name="object_4" pos="0.339062 0.288300 0.182610" quat="0.736290 -0.000008 -0.000004 0.676666">
			<geom friction="0.3 0.3 0.3" contype="3" conaffinity="3" mass="1." name="object_4" rgba="1 0 0. 1" size="0.03 0.05" type="cylinder" />
			<joint damping="0.5" stiffness="0.01" armature="0.1" name="object_4_free" type="free" />
		</body>
		<body name="object_5" pos="0.502650 0.295808 0.183032" quat="-0.676358 -0.000069 -0.000092 -0.736573">
			<geom friction="0.3 0.3 0.3" contype="3" conaffinity="3" mass="1." name="object_5" rgba="1 0 0. 1" size="0.03 0.05" type="cylinder" />
			<joint damping="0.5" stiffness="0.01" armature="0.1" name="object_5_free" type="free" />
		</body>
		<body name="object_6" pos="0.340950 -0.083205 0.182605" quat="-0.889162 -0.000001 -0.000003 0.457593">
			<geom friction="0.3 0.3 0.3" contype="3" conaffinity="3" mass="1." name="object_6" rgba="1 0 0. 1" size="0.03 0.05" type="cylinder" />
			<joint damping="0.5" stiffness="0.01" armature="0.1" name="object_6_free" type="free" />
		</body>
		<body name="object_7" pos="0.357197 0.075470 0.182602" quat="0.655222 -0.000004 0.000002 0.755437">
			<geom friction="0.3 0.3 0.3" contype="3" conaffinity="3" mass="1." name="object_7" rgba="1 0 0. 1" size="0.03 0.05" type="cylinder" />
			<joint damping="0.5" stiffness="0.01" armature="0.1" name="object_7_free" type="free" />
		</body>
		<body name="object_8" pos="0.550866 0.225629 0.182598" quat="-0.462232 -0.000001 -0.000008 -0.886759">
			<geom friction="0.3 0.3 0.3" contype="3" conaffinity="3" mass="1." name="object_8" rgba="1 0 0. 1" size="0.03 0.05" type="cylinder" />
			<joint damping="0.5" stiffness="0.01" armature="0.1" name="object_8_free" type="free" />
		</body>
		<body name="object_9" pos="0.545586 -0.014292 0.182593" quat="0.234882 -0.000010 -0.000001 -0.972024">
			<geom friction="0.3 0.3 0.3" contype="3" conaffinity="3" mass="1." name="object_9" rgba="1 0 0. 1" size="0.03 0.05" type="cylinder" />
			<joint damping="0.5" stiffness="0.01" armature="0.1" name="object_9_free" type="free" />
		</body>
		<body name="object_10" pos="0.457284 0.018987 0.182588" quat="-0.988592 0.000009 -0.000012 0.150618">
			<geom friction="0.3 0.3 0.3" contype="3" conaffinity="3" mass="1." name="object_10" rgba="1 0 0. 1" size="0.03 0.05" type="cylinder" />
			<joint damping="0.5" stiffness="0.01" armature="0.1" name="object_10_free" type="free" />
		</body>
		<body name="object_11" pos="0.473004 -0.041805 0.182582" quat="-0.744924 0.000002 -0.000001 0.667149">
			<geom friction="0.3 0.3 0.3" contype="3" conaffinity="3" mass="1." name="object_11" rgba="1 0 0. 1" size="0.03 0.05" type="cylinder" />
			<joint damping="0.5" stiffness="0.01" armature="0.1" name="object_11_free" type="free" />
		</body>
		<body name="object_12" pos="0.365049 0.210952 0.182575" quat="0.896363 0.000001 -0.000005 -0.443320">
			<geom friction="0.3 0.3 0.3" contype="3" conaffinity="3" mass="1." name="object_12" rgba="1 0 0. 1" size="0.03 0.05" type="cylinder" />
			<joint damping="0.5" stiffness="0.01" armature="0.1" name="object_12_free" type="free" />
		</body>
		<body name="object_13" pos="0.436522 0.307689 0.182567" quat="0.429313 -0.000002 -0.000006 -0.903156">
			<geom friction="0.3 0.3 0.3" contype="3" conaffinity="3" mass="1." name="object_13" rgba="1 0 0. 1" size="0.03 0.05" type="cylinder" />
			<joint damping="0.5" stiffness="0.01" armature="0.1" name="object_13_free" type="free" />
		</body>
		<body name="object_14" pos="0.316903 0.173571 0.182559" quat="-0.912338 0.000001 0.000020 -0.409438">
			<geom friction="0.3 0.3 0.3" contype="3" conaffinity="3" mass="1." name="object_14" rgba="1 0 0. 1" size="0.03 0.05" type="cylinder" />
			<joint damping="0.5" stiffness="0.01" armature="0.1" name="object_14_free" type="free" />
		</body>
		<body name="object_15" pos="0.391907 0.146424 0.182549" quat="-0.415041 0.000008 -0.000002 0.909803">
			<geom friction="0.3 0.3 0.3" contype="3" conaffinity="3" mass="1." name="object_15" rgba="1 0 0. 1" size="0.03 0.05" type="cylinder" />
			<joint damping="0.5" stiffness="0.01" armature="0.1" name="object_15_free" type="free" />
		</body>
		<body name="object_16" pos="0.402733 -0.053481 0.182538" quat="-0.987124 0.000005 0.000001 0.159954">
			<geom friction="0.3 0.3 0.3" contype="3" conaffinity="3" mass="1." name="object_16" rgba="1 0 0. 1" size="0.03 0.05" type="cylinder" />
			<joint damping="0.5" stiffness="0.01" armature="0.1" name="object_16_free" type="free" />
		</body>
		<body name="object_17" pos="0.487316 0.183134 0.182527" quat="-0.988222 -0.000003 -0.000007 -0.153028">
			<geom friction="0.3 0.3 0.3" contype="3" conaffinity="3" mass="1." name="object_17" rgba="1 0 0. 1" size="0.03 0.05" type="cylinder" />
			<joint damping="0.5" stiffness="0.01" armature="0.1" name="object_17_free" type="free" />
		</body>
		<body name="object_18" pos="0.316752 -0.006138 0.182516" quat="0.313455 0.000002 -0.000002 -0.949603">
			<geom friction="0.3 0.3 0.3" contype="3" conaffinity="3" mass="1." name="object_18" rgba="1 0 0. 1" size="0.03 0.05" type="cylinder" />
			<joint damping="0.5" stiffness="0.01" armature="0.1" name="object_18_free" type="free" />
		</body>
		<body name="object_19" pos="0.548336 0.049993 0.182505" quat="0.459088 -0.000005 -0.000002 -0.888391">
			<geom friction="0.3 0.3 0.3" contype="3" conaffinity="3" mass="1." name="object_19" rgba="1 0 0. 1" size="0.03 0.05" type="cylinder" />
			<joint damping="0.5" stiffness="0.01" armature="0.1" name="object_19_free" type="free" />
		</body>
		<body name="object_20" pos="0.395331 0.007827 0.182495" quat="-0.141675 -0.000000 -0.000003 -0.989913">
			<geom friction="0.3 0.3 0.3" contype="3" conaffinity="3" mass="1." name="object_20" rgba="1 0 0. 1" size="0.03 0.05" type="cylinder" />
			<joint damping="0.5" stiffness="0.01" armature="0.1" name="object_20_free" type="free" />
		</body>
		<include file="robot/include/gripper_only_planar_robot.xml" />
		<include file="include/small_shelf.xml" />
	</worldbody>
</mujoco>
